{
	"last_edited": "2022-09-09T15:52:00+09:00",
	"ougi": [
		{
			"name": "炎獄嵐",
			"text": "火属性ダメージ(大)\n味方全体の炎陣を消去"
		}
	],
	"abilities": [
		{
			"name": "陣開(1アビ)",
			"text": "敵全体に火属性ダメージ\n味方全体に炎陣を追加(2ターン/最大3個)",
			"cd": "6"
		},
		{
			"name": "刻炎(2アビ)",
			"text": "味方全体に炎陣を追加(2ターン/最大3個)",
			"cd": "5"
		},
		{
			"name": "追灼(3アビ)",
			"text": "敵に火属性ダメージ\n味方全体の炎陣効果を3ターン延長",
			"cd": "7"
		}
	],
	"support": [
		{
			"name": "インプロージョン",
			"text": "味方に付与されている炎陣の数に応じて\n奥義ダメージUP/奥義ダメージ上限UP"
		},
		{
			"name": "炎陣",
			"text": "炎陣効果中の味方は\n・火属性攻撃力UP\n・ダブルアタック確率UP\n(最大Lv3まで上昇)"
		}
	]
}