{
	"last_edited": "2022-09-09T15:52:00+09:00",
	"ougi": [
		{
			"name": "アウフヘーベン",
			"text": "光属性ダメージ(大)\n自分のアビリティ再使用間隔を1ターン短縮"
		}
	],
	"abilities": [
		{
			"name": "さてさて、お一つ問うね(1アビ)",
			"text": "味方に問いかける\n◆フィラソピラ以外のバトルメンバーが最初に使用したアビリティの種類に応じた効果が発動",
			"cd": "7"
		},
		{
			"name": "ならなら、も一つ問うね(2アビ)",
			"text": "敵に問いかける\n◆敵が通常攻撃または特殊技を使用時に効果が発動(1ターン)",
			"cd": "7"
		},
		{
			"name": "パンタレイ(3アビ)",
			"text": "自分の他のアビリティが即時使用可能になる",
			"cd": "10"
		}
	],
	"support": [
		{
			"name": "止まらぬ探求",
			"text": "アビリティを使用する度にクリュプトンの回転速度が上昇\n◆クリュプトンの回転速度に応じて自分の連続攻撃確率UP(最大5)"
		},
		{
			"name": "だから、私は考え続けるの",
			"text": "サブメンバー時\n味方全体の闇属性ダメージ軽減"
		}
	]
}