{
	"last_edited": "2022-12-08T21:20:00+09:00",
	"ougi": [
		{
			"name": "創世のルミノックス",
			"text": "土属性ダメージ(倍率5.0/特大)\n自分に\n・奥義ゲージUP(20%)\n・HP回復(最大4000)\n・荒土の刻印を1つ付与(最大5/消去不可)"
		}
	],
	"abilities": [
		{
			"name": "ブローナド・ノルン(1アビ)",
			"text": "味方全体にウルザブルン効果(消去不可/5ターン)\n・攻撃力UP(50%/攻刃枠)\n・防御力UP(50%)\n味方全体に\n・奥義ゲージ上昇量UP(25%/5ターン)\n・荒土の刻印を1つ付与(最大5/消去不可)",
			"cd": "6"
		},
		{
			"name": "ジグラット(通常時2アビ)エ・ウ・ニル(荒土の刻印32アビ)",
			"text": "▼\n土属性キャラのクリティカル確率UP(倍率30%/発動率80%/3ターン)\n自分以外の味方全体にバリア効果(3500/3ターン)\n◆奥義ゲージを20%消費/荒土の刻印が3以上の時、このアビリティが「エ・ウ・ニル」に変化\nエ・ウ・ニル\n・土属性キャラのクリティカル確率UP(倍率30%/発動率80%/3ターン)\n・自分以外の味方全体にバリア効果(3500/永続)\n・自分に創樹の大器効果(3ターン/消去不可)\n◆創樹の大器効果中は\n・かばう効果(単体)\n・ブロック効果(50%)\n・被ダメージ時にターゲットに関わらず土属性4回ダメージ/自身のアビリティ再使用感覚を1ターン短縮(1倍/合計上限約68万)",
			"cd": "6"
		},
		{
			"name": "ケラスス・グラティア(3アビ)",
			"text": "味方全体のHP回復(500)\n再生効果(400/3ターン)\n弱体効果を1つ回復",
			"cd": "7"
		}
	],
	"support": [
		{
			"name": "慈愛の大樹",
			"text": "敵のターゲットにされやすい(約60～80%)\n※4人編成で100回中46回被弾\n被ダメージ時の奥義ゲージ上昇量UP(100%)"
		},
		{
			"name": "アニマ・アエテルヌス",
			"text": "土属性キャラが\n・水属性の敵に対して与ダメージUP(20%/天司武器と同枠共存不可)\n・それぞれの荒土の刻印の数に応じて回復性能UP(刻印1×2%/最大10%)\n◆刻印の回復性能UPは自分がサブメンバーにいる場合でも発動"
		}
	]
}